nlpforturkish/offensive_language_detect.py
nlpforturkish/twitterAPILib.py
nlpforturkish-0.1.1.dist-info/METADATA
nlpforturkish-0.1.1.dist-info/WHEEL
nlpforturkish-0.1.1.dist-info/top_level.txt
nlpforturkish-0.1.1.dist-info/RECORD
