Metadata-Version: 2.1
Name: nlpforturkish
Version: 0.1.1
Summary: The aim of the NLPforTurkish library is to assist people interested in artificial intelligence by supporting the Turkish NLP area, which will benefit many people, particularly those who want to work on Turkish NLP.
Author: Furkan Kesgin
Author-email: furkan_bfk@hotmail.com
Classifier: Development Status :: 3 - Alpha
Classifier: Intended Audience :: Developers
Classifier: Topic :: Software Development :: Build Tools
Classifier: License :: OSI Approved :: MIT License
Classifier: Programming Language :: Python :: 3
Classifier: Programming Language :: Python :: 3.6
Classifier: Programming Language :: Python :: 3.7
Classifier: Programming Language :: Python :: 3.8
Requires-Dist: pandas
Requires-Dist: scikit-learn
Requires-Dist: matplotlib
Requires-Dist: lazypredict
Requires-Dist: tweepy
